advprep/__init__.py
advprep/encoding.py
advprep/feature_engineering.py
advprep/imputation.py
advprep/pipeline.py
advprep/scaling.py
advprep-0.1.2.dist-info/licenses/LICENSE
advprep-0.1.2.dist-info/METADATA
advprep-0.1.2.dist-info/WHEEL
advprep-0.1.2.dist-info/top_level.txt
advprep-0.1.2.dist-info/RECORD
